{
  "X": "",
  "Блок кода": "",
  "Блок текста": "",
  "Веб": "",
  "Вставьте ссылку на изображение": "",
  "Дизайн": "",
  "Добавить поле": "",
  "Заголовок": "",
  "Заголовок статьи": "",
  "Здоровье": "",
  "Изображение": "",
  "Кибербезопасность": "",
  "Код": "",
  "Наука": "",
  "Подзаголовок статьи": "",
  "Подпись": "",
  "Редактирование статьи с ID = ": "",
  "Создание статьи": "",
  "Создать статью": "",
  "Ссылка на изображение статьи": "",
  "Текст": "",
  "Тема статьи": "",
  "Экономика": ""
}
